crispyn/__init__.py
crispyn/additions.py
crispyn/correlations.py
crispyn/normalizations.py
crispyn/weighting_methods.py
crispyn/mcda_methods/__init__.py
crispyn/mcda_methods/mcda_method.py
crispyn/mcda_methods/vikor.py
crispyn/mcda_methods/vikor_smaa.py
crispyn-0.0.6.dist-info/LICENSE
crispyn-0.0.6.dist-info/METADATA
crispyn-0.0.6.dist-info/WHEEL
crispyn-0.0.6.dist-info/top_level.txt
crispyn-0.0.6.dist-info/RECORD
